aztools/__init__.py
aztools/defender_portal.py
aztools/loganalytics.py
aztools/oauth.py
h2w_aztools-1.2.dist-info/licenses/LICENSE.txt
h2w_aztools-1.2.dist-info/METADATA
h2w_aztools-1.2.dist-info/WHEEL
h2w_aztools-1.2.dist-info/top_level.txt
h2w_aztools-1.2.dist-info/RECORD
