Metadata-Version: 2.4
Name: h2w-aztools
Version: 1.2
Summary: Python Blue Teamer Library for Interacting with Azure API
Author: Harvey Wargo
License: MIT License
Project-URL: Homepage, https://github.com/harveywargo2/h2w-aztools
Keywords: Azure,Sentinel,MDE,M365D
Classifier: Programming Language :: Python
Classifier: Programming Language :: Python :: 3
Requires-Python: >=3.8
License-File: LICENSE.txt
Requires-Dist: requests
Requires-Dist: pandas
Requires-Dist: datetime
Dynamic: license-file
